{"type":"FeatureCollection","features":[{"type":"Feature","properties":{"author":"Jose","name":"Hall dpto. Química Física","file":"pano_1434608676738.jpg","date":"26/6/2015 8:24:47 AM","code":"0008PS008"},"geometry":{"type":"Point","coordinates":[-0.51487773,38.38729055]}}]}
