{
  "type": "FeatureCollection",
  "features": [
    {

      "type": "Feature",
      "properties": {
		"file": "PANO_20150505_113912kk.jpg", 
        "author": "Jose", 
        "code": "0037PB009",
        "name": "Institutos Universitarios",
        "date": "2015/05/05"
      },
      "geometry": {
        "type": "Point",
        "coordinates": [
          -0.5119693279266356,
          38.38471925895566
        ]
      }
    },
    {

      "type": "Feature",
      "properties": {
		"file": "PANO_20150505_113912kk.jpg", 
        "author": "Jose", 
        "code": "0037PB009",
        "name": "Institutos Universitarios",
        "date": "2015/05/05"
      },
      "geometry": {
        "type": "Point",
        "coordinates": [
          -0.5121839046478271,
          38.38320966693145
        ]
      }
    },
    {

      "type": "Feature",
      "properties": {
		"file": "pano4.jpg", 
        "author": "Jose", 
        "code": "0037PB009",
        "name": "Institutos Universitarios",
        "date": "2015/05/05"
      },
      "geometry": {
        "type": "Point",
        "coordinates": [
          -0.5112504959106445,
          38.38244855148512
        ]
      }
    },
   {

      "type": "Feature",
      "properties": {
		"file": "pano4.jpg", 
        "author": "Jose", 
        "code": "0037PB009",
        "name": "Institutos Universitarios",
        "date": "2015/05/05"
      },
      "geometry": {
        "type": "Point",
        "coordinates": [
          -0.511341,
          38.382489 
        ]
      }
    }    
  ]
}
