{
  "type": "FeatureCollection",
  "features": [
    {
      "type": "Feature",
      "properties": {
        "img": "PANO_20150505_113912kk.jpg",
        "name": "patio interior IU",
        "code": "0000PB270",
        "date": "2015-05-05"
      },
      "geometry": {
        "type": "Point",
        "coordinates": [
          -0.5113121867179871,
          38.382450654024986
        ]
      }
    },
    {
      "type": "Feature",
      "properties": {
        "img": "PANO_20150505_113912kk.jpg",
        "name": "Despacho IU",
        "code": "0037P1013",
        "date": "2015-05-05"
      },
      "geometry": {
        "type": "Point",
        "coordinates": [
          -0.5111485719680786,
          38.3823896803434
        ]
      }
    },
    {
      "type": "Feature",
      "properties": {
        "img": "PANO_20150505_113912kk.jpg",
        "name": "Laboratorio Geomatica",
        "code": "0037P1015",
        "date": "2015-05-06"
      },
      "geometry": {
        "type": "Point",
        "coordinates": [
          -0.5111244320869446,
          38.38230347608522
        ]
      }
    }
  ]
}
