{"type":"FeatureCollection","features":[{"type":"Feature",
"properties":{"file":"PANO_20150505_113912kk.jpg","author":"Jose","code":"0037PB009","name":"Institutos Universitarios","date":"2015/05/05"},"geometry":{"type":"Point","coordinates":[-0.5119693279266356,38.38471925895566]}},{"type":"Feature",
"properties":{"file":"PANO_20150505_113912kk.jpg","author":"Jose","code":"0037PB009","name":"Institutos Universitarios","date":"2015/05/05"},"geometry":{"type":"Point","coordinates":[-0.5121839046478271,38.38320966693145]}},{"type":"Feature",
"properties":{"file":"pano4.jpg","author":"Jose","code":"0037PB009","name":"Institutos Universitarios","date":"2015/05/05"},"geometry":{"type":"Point","coordinates":[-0.5112504959106445,38.38244855148512]}},{"type":"Feature",
"properties":{"file":"pano4.jpg","author":"Jose","code":"0037PB009","name":"Institutos Universitarios","date":"2015/05/05"},"geometry":{"type":"Point","coordinates":[-0.511341,38.382489]}},{"type":"Feature",
"properties":{"author":"Jose","name":"cafeteria","file":"pano_1434539486071.jpg","date":"17/6/2015 1:11:36 PM","code":"0000PB290"},"geometry":{"type":"Point","coordinates":[-0.5159282684326171,38.38472766885085]}},{"type":"Feature",
"properties":{"author":"Jose","name":"geografia","file":"pano_1434539589466.jpg","date":"17/6/2015 1:13:30 PM","code":"0000PB288"},"geometry":{"type":"Point","coordinates":[-0.5147159099578857,38.38562962443171]}}]}
