{"type":"FeatureCollection","features":[{"type":"Feature","properties":{"author":"Jose","name":"Patio institutos","file":"pano_1434608676738.jpg","date":"18/6/2015 8:24:47 AM","code":"0000PB270"},"geometry":{"type":"Point","coordinates":[-0.5113175511360168,38.382456961644294]}},{"type":"Feature","properties":{"author":"Jose","name":"Despacho","file":"pano_1434611891163.jpg","date":"18/6/2015 9:18:31 AM","code":"0019PB022"},"geometry":{"type":"Point","coordinates":[-0.5141754448413849,38.3855760120018]}},{"type":"Feature","properties":{"author":"Jose","name":"Derecho","file":"pano_1434613345625.jpg","date":"18/6/2015 9:42:54 AM","code":"0011PB117"},"geometry":{"type":"Point","coordinates":[-0.5169273912906647,38.38538784257057]}}]}