{"type":"FeatureCollection","features":[{"type":"Feature","properties":{"author":"Jose","name":"cafeteria","file":"pano_1434539486071.jpg","date":"17/6/2015 1:11:36 PM","code":"0000PB290"},"geometry":{"type":"Point","coordinates":[-0.5159282684326171,38.38472766885085]}},{"type":"Feature","properties":{"author":"Jose","name":"geografia","file":"pano_1434539589466.jpg","date":"17/6/2015 1:13:30 PM","code":"0000PB288"},"geometry":{"type":"Point","coordinates":[-0.5147159099578857,38.38562962443171]}},{"type":"Feature","properties":{"author":"Jose","name":"Patio institutos universitarios","file":"pano_1434607677030.jpg","date":"18/6/2015 8:08:35 AM","code":"0000PB270"},"geometry":{"type":"Point","coordinates":[-0.5113282799720764,38.382456961644294]}}]}