{"type":"FeatureCollection","features":[{"type":"Feature","properties":{"author":"Jose","name":"Hall dpto. Química Física","file":"pano_1434608676738.jpg","date":"26/6/2015 8:24:47 AM","code":"0007P4055"},"geometry":{"type":"Point","coordinates":[-0.51618600180,38.38687691329]}}]}
